katcrypt/__init__.py
katcrypt/info.py
katcrypt/test.py
katcrypt/utils.py
katcrypt/ciphers/__init__.py
katcrypt/ciphers/aes.py
katcrypt/ciphers/mars.py
katcrypt/ciphers/threefish.py
katcrypt/constants/__init__.py
katcrypt/constants/aes_tables.py
katcrypt/constants/mars_tables.py
katcrypt/constants/threefish_tables.py
katcrypt/modes/__init__.py
katcrypt/modes/cbc.py
katcrypt/modes/cfb.py
katcrypt/modes/ctr.py
katcrypt/modes/ecb.py
katcrypt/modes/gcm.py
katcrypt/modes/ofb.py
katcrypt/test_vectors/__init__.py
katcrypt/test_vectors/aes_test_vectors.py
katcrypt/test_vectors/mars_test_vectors.py
katcrypt/test_vectors/threefish_test_vectors.py
katcrypt-0.1.4.dist-info/licenses/LICENSE
katcrypt-0.1.4.dist-info/METADATA
katcrypt-0.1.4.dist-info/WHEEL
katcrypt-0.1.4.dist-info/top_level.txt
katcrypt-0.1.4.dist-info/RECORD
