Metadata-Version: 2.4
Name: katcrypt
Version: 0.1.4
Summary: A pure Python encryption library supporting a variety of algorithms and modes
Home-page: https://github.com/hashwalker/katcrypt
Author: hashwalker
Author-email: hashwalker125@protonmail.com
Project-URL: Source, https://github.com/hashwalker/katcrypt
Project-URL: Documentation, https://github.com/hashwalker/katcrypt#readme
Keywords: cryptography,encryption,aes,mars,threefish,block cipher,security,crypto
Classifier: License :: OSI Approved :: MIT License
Classifier: Programming Language :: Python :: 3
Classifier: Topic :: Security :: Cryptography
Requires-Python: >=3.7
License-File: LICENSE
Provides-Extra: dev
Requires-Dist: pytest>=6.0; extra == "dev"
Requires-Dist: pytest-cov; extra == "dev"
Dynamic: author
Dynamic: author-email
Dynamic: classifier
Dynamic: description
Dynamic: description-content-type
Dynamic: home-page
Dynamic: keywords
Dynamic: license-file
Dynamic: project-url
Dynamic: provides-extra
Dynamic: requires-python
Dynamic: summary
